ezpq/Job.py
ezpq/Plot.py
ezpq/Queue.py
ezpq/__init__.py
ezpq-0.2.2.dist-info/LICENSE
ezpq-0.2.2.dist-info/METADATA
ezpq-0.2.2.dist-info/WHEEL
ezpq-0.2.2.dist-info/top_level.txt
ezpq-0.2.2.dist-info/RECORD
