Metadata-Version: 2.1
Name: ezpq
Version: 0.2.2
Summary: an easy parallel queueing system
Home-page: https://www.github.com/dm3ll3n/ezpq
Author: Donald Mellenbruch
Author-email: dmellenbruch@outlook.com
License: MIT
Keywords: Parallel,Queue
Platform: UNKNOWN
Provides-Extra: plot
Requires-Dist: numpy ; extra == 'plot'
Requires-Dist: pandas ; extra == 'plot'
Requires-Dist: matplotlib ; extra == 'plot'
Requires-Dist: plotnine ; extra == 'plot'
